{"success": true, "data": [{"description": "Hint for NeuralFluxCorp", "date": "2025-10-19T12:24:49.152254+00:00", "id": 49, "team_id": 350, "category": "hints", "name": "Hint 2", "user_id": 952, "requirements": null, "type": "standard", "user": 952, "icon": null, "value": 0, "team": 350}, {"description": "Hint for Puppeteer", "date": "2025-10-19T11:55:12.986457+00:00", "id": 3, "team_id": 350, "category": "hints", "name": "Hint 1", "user_id": 952, "requirements": null, "type": "standard", "user": 952, "icon": null, "value": 0, "team": 350}], "meta": {"count": 2}}
