{"success": true, "data": [{"user": {"name": "GodInReach", "id": 1486}, "date": "2025-10-18T15:07:02.683698+00:00", "id": 11197, "challenge": {"name": "Guess ??", "category": "Rev", "value": 1000, "id": 34}, "team": {"name": "CYBERBEINGS", "id": 647}, "challenge_id": 34, "type": "correct"}, {"user": {"name": "GodInReach", "id": 1486}, "date": "2025-10-18T13:43:53.531927+00:00", "id": 10476, "challenge": {"name": "Baby Sharingan", "category": "Crypto", "value": 500, "id": 18}, "team": {"name": "CYBERBEINGS", "id": 647}, "challenge_id": 18, "type": "correct"}], "meta": {"count": 2}}
