{"success": true, "data": [{"user": {"name": "Itz_me_strikerr", "id": 884}, "date": "2025-10-19T13:17:36.879464+00:00", "id": 35031, "challenge": {"name": "Quantum Memory", "category": "Pwn", "value": 2000, "id": 46}, "team": {"name": "Payatu Bandits", "id": 371}, "challenge_id": 46, "type": "correct"}, {"user": {"name": "Itz_me_strikerr", "id": 884}, "date": "2025-10-19T07:57:13.098857+00:00", "id": 29098, "challenge": {"name": "Seccomp Jail", "category": "Pwn", "value": 2500, "id": 48}, "team": {"name": "Payatu Bandits", "id": 371}, "challenge_id": 48, "type": "correct"}, {"user": {"name": "Itz_me_strikerr", "id": 884}, "date": "2025-10-18T16:58:08.905962+00:00", "id": 16428, "challenge": {"name": "KGF 2.0", "category": "DFIR", "value": 2000, "id": 39}, "team": {"name": "Payatu Bandits", "id": 371}, "challenge_id": 39, "type": "correct"}, {"user": {"name": "Itz_me_strikerr", "id": 884}, "date": "2025-10-18T09:24:31.528545+00:00", "id": 7795, "challenge": {"name": "KGF 1.0", "category": "DFIR", "value": 1500, "id": 38}, "team": {"name": "Payatu Bandits", "id": 371}, "challenge_id": 38, "type": "correct"}, {"user": {"name": "Itz_me_strikerr", "id": 884}, "date": "2025-10-18T06:58:08.714802+00:00", "id": 5293, "challenge": {"name": "Guess ??", "category": "Rev", "value": 1000, "id": 34}, "team": {"name": "Payatu Bandits", "id": 371}, "challenge_id": 34, "type": "correct"}, {"user": {"name": "Itz_me_strikerr", "id": 884}, "date": "2025-10-18T04:34:19.680179+00:00", "id": 2119, "challenge": {"name": "Mauryan Imperial Archives", "category": "Pwn", "value": 1000, "id": 10}, "team": {"name": "Payatu Bandits", "id": 371}, "challenge_id": 10, "type": "correct"}], "meta": {"count": 6}}
