{"success": true, "data": [{"user": {"name": "SR", "id": 842}, "date": "2025-10-19T15:01:32.689517+00:00", "id": 37120, "challenge": {"name": "RecoverFS", "category": "DFIR", "value": 1750, "id": 41}, "team": {"name": "root@void", "id": 357}, "challenge_id": 41, "type": "correct"}, {"user": {"name": "SpeedxThunder", "id": 474}, "date": "2025-10-19T12:39:53.253532+00:00", "id": 34291, "challenge": {"name": "0x0f05", "category": "Pwn", "value": 2000, "id": 47}, "team": {"name": "root@void", "id": 357}, "challenge_id": 47, "type": "correct"}, {"user": {"name": "SR", "id": 842}, "date": "2025-10-19T11:54:18.732066+00:00", "id": 33454, "challenge": {"name": "Seccomp Jail", "category": "Pwn", "value": 2500, "id": 48}, "team": {"name": "root@void", "id": 357}, "challenge_id": 48, "type": "correct"}, {"user": {"name": "SpeedxThunder", "id": 474}, "date": "2025-10-19T07:20:08.237365+00:00", "id": 28359, "challenge": {"name": "OAEPsy", "category": "Crypto", "value": 2000, "id": 49}, "team": {"name": "root@void", "id": 357}, "challenge_id": 49, "type": "correct"}, {"user": {"name": "SR", "id": 842}, "date": "2025-10-19T02:11:28.217742+00:00", "id": 23631, "challenge": {"name": "Optim", "category": "Rev", "value": 1500, "id": 35}, "team": {"name": "root@void", "id": 357}, "challenge_id": 35, "type": "correct"}, {"user": {"name": "SR", "id": 842}, "date": "2025-10-18T16:27:11.030704+00:00", "id": 15047, "challenge": {"name": "KGF 2.0", "category": "DFIR", "value": 2000, "id": 39}, "team": {"name": "root@void", "id": 357}, "challenge_id": 39, "type": "correct"}, {"user": {"name": "SpeedxThunder", "id": 474}, "date": "2025-10-18T15:39:29.322380+00:00", "id": 11670, "challenge": {"name": "Blazing Hot", "category": "OSINT", "value": 1500, "id": 20}, "team": {"name": "root@void", "id": 357}, "challenge_id": 20, "type": "correct"}, {"user": {"name": "SpeedxThunder", "id": 474}, "date": "2025-10-18T14:40:26.508933+00:00", "id": 11003, "challenge": {"name": "Moby Dock 1", "category": "B2R", "value": 1500, "id": 24}, "team": {"name": "root@void", "id": 357}, "challenge_id": 24, "type": "correct"}, {"user": {"name": "crownedhog", "id": 597}, "date": "2025-10-18T09:58:25.121883+00:00", "id": 8255, "challenge": {"name": "\u691c\u8a3c", "category": "Misc", "value": 500, "id": 21}, "team": {"name": "root@void", "id": 357}, "challenge_id": 21, "type": "correct"}, {"user": {"name": "SR", "id": 842}, "date": "2025-10-18T08:04:12.337676+00:00", "id": 6394, "challenge": {"name": "KGF 1.0", "category": "DFIR", "value": 1500, "id": 38}, "team": {"name": "root@void", "id": 357}, "challenge_id": 38, "type": "correct"}, {"user": {"name": "SpeedxThunder", "id": 474}, "date": "2025-10-18T05:20:16.172076+00:00", "id": 3145, "challenge": {"name": "High Rise ", "category": "OSINT", "value": 1000, "id": 36}, "team": {"name": "root@void", "id": 357}, "challenge_id": 36, "type": "correct"}, {"user": {"name": "SR", "id": 842}, "date": "2025-10-18T05:17:46.777286+00:00", "id": 3072, "challenge": {"name": "Baby Sharingan", "category": "Crypto", "value": 500, "id": 18}, "team": {"name": "root@void", "id": 357}, "challenge_id": 18, "type": "correct"}, {"user": {"name": "SR", "id": 842}, "date": "2025-10-18T05:00:57.874054+00:00", "id": 2603, "challenge": {"name": "Wash Away ", "category": "OSINT", "value": 1500, "id": 16}, "team": {"name": "root@void", "id": 357}, "challenge_id": 16, "type": "correct"}, {"user": {"name": "SpeedxThunder", "id": 474}, "date": "2025-10-18T04:43:07.522667+00:00", "id": 2247, "challenge": {"name": "Quantum Memory", "category": "Pwn", "value": 2000, "id": 46}, "team": {"name": "root@void", "id": 357}, "challenge_id": 46, "type": "correct"}, {"user": {"name": "SpeedxThunder", "id": 474}, "date": "2025-10-18T04:18:51.674158+00:00", "id": 1781, "challenge": {"name": "Mauryan Imperial Archives", "category": "Pwn", "value": 1000, "id": 10}, "team": {"name": "root@void", "id": 357}, "challenge_id": 10, "type": "correct"}, {"user": {"name": "SR", "id": 842}, "date": "2025-10-18T04:10:42.176759+00:00", "id": 1603, "challenge": {"name": "Guess ??", "category": "Rev", "value": 1000, "id": 34}, "team": {"name": "root@void", "id": 357}, "challenge_id": 34, "type": "correct"}], "meta": {"count": 16}}
