{"success": true, "data": [{"user": {"name": "OldBear", "id": 638}, "date": "2025-10-18T11:31:34.687662+00:00", "id": 9091, "challenge": {"name": "Mauryan Imperial Archives", "category": "Pwn", "value": 1000, "id": 10}, "team": {"name": "Cincinat", "id": 276}, "challenge_id": 10, "type": "correct"}, {"user": {"name": "OldBear", "id": 638}, "date": "2025-10-18T06:50:05.552850+00:00", "id": 5172, "challenge": {"name": "Guess ??", "category": "Rev", "value": 1000, "id": 34}, "team": {"name": "Cincinat", "id": 276}, "challenge_id": 34, "type": "correct"}], "meta": {"count": 2}}
